fastilybot/__init__.py
fastilybot/__main__.py
fastilybot/bots.py
fastilybot/constants.py
fastilybot/core.py
fastilybot/reports.py
fastilybot-2.2.0.dist-info/LICENSE.md
fastilybot-2.2.0.dist-info/METADATA
fastilybot-2.2.0.dist-info/WHEEL
fastilybot-2.2.0.dist-info/entry_points.txt
fastilybot-2.2.0.dist-info/top_level.txt
fastilybot-2.2.0.dist-info/RECORD
