Metadata-Version: 2.1
Name: fastilybot
Version: 2.2.0
Summary: Fastily's Wikipedia Bots
Home-page: https://github.com/fastily/fastilybot
Author: Fastily
Author-email: fastily@users.noreply.github.com
Project-URL: Bug Tracker, https://github.com/fastily/fastilybot/issues
Classifier: Natural Language :: English
Classifier: Programming Language :: Python :: 3
Classifier: Programming Language :: Python :: 3.11
Classifier: License :: OSI Approved :: GNU General Public License v3 (GPLv3)
Classifier: Operating System :: OS Independent
Requires-Python: >=3.11
License-File: LICENSE.md
Requires-Dist: pwiki
Requires-Dist: rich
